namsorclient/__init__.py
namsorclient/country_codes.py
namsorclient/helpers.py
namsorclient/models.py
namsorclient/request_objects.py
namsorclient/tests/__init__.py
namsorclient/tests/test_models.py
namsorclient/tests/test_request_objects.py
namsor_client-0.0.6.dist-info/LICENSE
namsor_client-0.0.6.dist-info/METADATA
namsor_client-0.0.6.dist-info/WHEEL
namsor_client-0.0.6.dist-info/top_level.txt
namsor_client-0.0.6.dist-info/RECORD
