Metadata-Version: 2.1
Name: namsor-client
Version: 0.0.6
Summary: A Wrapper for the Namsor Classification API
Home-page: https://github.com/JosephPallipadan/Namsor-API-Wrapper-Python
Author: Joseph Pallipadan
Author-email: pallipadanjoseph@gmail.com
License: UNKNOWN
Platform: UNKNOWN
Classifier: Programming Language :: Python :: 3
Classifier: License :: OSI Approved :: MIT License
Classifier: Operating System :: OS Independent
Requires-Dist: requests
